namecase.py
namecase-0.3.3.dist-info/LICENSE
namecase-0.3.3.dist-info/METADATA
namecase-0.3.3.dist-info/WHEEL
namecase-0.3.3.dist-info/entry_points.txt
namecase-0.3.3.dist-info/RECORD
